json_explore.py
json_explore-2.0.1.dist-info/METADATA
json_explore-2.0.1.dist-info/WHEEL
json_explore-2.0.1.dist-info/entry_points.txt
json_explore-2.0.1.dist-info/top_level.txt
json_explore-2.0.1.dist-info/RECORD
