Metadata-Version: 2.4
Name: json-explore
Version: 2.0.1
Summary: A lightweight CLI tool for interactively exploring JSON files and dictionaries.
Home-page: https://github.com/mlraburn/json-CLI
Author: Matthew Raburn
Project-URL: Source Code, https://github.com/mlraburn/json_CLI
Classifier: Programming Language :: Python :: 3
Classifier: License :: OSI Approved :: MIT License
Classifier: Operating System :: OS Independent
Classifier: Development Status :: 5 - Production/Stable
Classifier: Intended Audience :: Developers
Classifier: Topic :: Software Development :: Libraries :: Python Modules
Requires-Python: >=3.6
Dynamic: author
Dynamic: classifier
Dynamic: description
Dynamic: description-content-type
Dynamic: home-page
Dynamic: project-url
Dynamic: requires-python
Dynamic: summary
